Workbook

Sheet 00_Portada y control
B5: PROYECTO SYNTRO
B6: Matriz de Riesgos
B7: Documento de gestión · Metodología Cascada (SDLC)
B10: Campo | C10: Información
B11: Organización beneficiaria | C11: Hospital Dr. Sótero del Río
B12: Proyecto | C12: SYNTRO
B13: Código documental | C13: SYNTRO-PM-005
B14: Versión / estado | C14: v0.3 · Borrador para revisión
B15: Fecha | C15: 11-10-2026
B16: Directora del Proyecto | C16: Constanza Gaete
B17: Responsable de elaboración | C17: Antonia Pacheco
B18: Patrocinador institucional | C18: Jefatura del Departamento de Tecnologías de la Información
B19: Patrocinador funcional | C19: Coordinador de Proyectos y Administrador de Contratos TIC
B20: Contraparte técnica principal | C20: Jefatura de la Unidad Infraestructura, Redes y Soporte
B21: Equipo ejecutor | C21: Antonia Pacheco · Constanza Gaete · Paolo Vilches
B23: Propósito
B24: Identificar, valorar y dar seguimiento a los riesgos que podrían afectar el alcance, plazo, calidad, seguridad, datos, infraestructura y aceptación del Proyecto SYNTRO. La matriz utiliza probabilidad e impacto en escala de 1 a 5, calcula la exposición inicial (P × I) y registra la respuesta, contingencia y riesgo residual.
B28: Control documental
B29: Versión | C29: Fecha | D29: Responsable | E29: Descripción del cambio | G29: Estado | H29: Aprobación
B30: 0.1 | C30: 11-10-2026 | D30: Antonia Pacheco | E30: Creación de la matriz inicial de riesgos, escalas, resumen y trazabilidad con la EDT. | G30: Borrador | H30: Pendiente
B31: 0.2 | C31: 11-10-2026 | D31: Antonia Pacheco | E31: Consolidación de la matriz inicial con 22 riesgos adicionales/aportados; eliminación de duplicados, reformulación específica y tratamiento del riesgo por cambios de edificios/containers. | G31: Borrador | H31: Pendiente
B32: 0.3 | C32: 12-10-2026 | D32: Antonia Pacheco | E32: Se incorpora hoja “Mapa de Riesgos” con matriz visual Probabilidad × Impacto, niveles por color y detalle de riesgos. | G32: Borrador | H32: Pendiente
B34: Nota: La valoración contenida en esta versión es una línea base inicial y debe revisarse periódicamente durante el ciclo de vida del proyecto.

Sheet Matriz de Riesgos
A1: SYNTRO · MATRIZ DE RIESGOS DEL PROYECTO
A2: Versión 0.3 · Matriz consolidada con mapa visual Probabilidad × Impacto. La valoración inicial y residual debe revisarse periódicamente con el equipo y las contrapartes.
A4: ID | B4: Categoría | C4: Riesgo | D4: Causa / origen | E4: Consecuencia | F4: Prob. | G4: Impacto | H4: Exposición | I4: Nivel | J4: Estrategia | K4: Respuesta preventiva / mitigación | L4: Plan de contingencia | M4: Responsable | N4: Indicador / disparador | O4: Estado | P4: EDT relacionada | Q4: Prob. residual | R4: Impacto residual | S4: Riesgo residual
A5: R-01 | B5: Técnico / Datos espaciales | C5: La información espacial inicial (planos, edificios, pisos, salas y containers) es incompleta, desactualizada o insuficientemente precisa para construir el mapa y validar rutas. | D5: Los antecedentes físicos pueden provenir de fuentes heterogéneas y no siempre reflejar la configuración vigente del recinto. | E5: El mapa puede iniciar con ubicaciones imprecisas y las rutas físicas podrían no ser verificables para todas las áreas. | F5: 4 | G5: 4 | H5: =F5*G5 -> 16 | I5: =IF(H5>=15,"Crítico",IF(H5>=10,"Alto",IF(H5>=5,"Medio","Bajo"))) -> Crítico | J5: Mitigar | K5: Solicitar y validar la mejor línea base espacial disponible; distinguir jerarquía lógica de geometría/rutas; definir un nivel mínimo viable edificio/piso/sala cuando no exista información suficiente para rutas. | L5: Habilitar el sector con jerarquía básica y marcar rutas/planos como pendientes de validación, sin bloquear el resto del inventario. | M5: Contraparte Infraestructura / Equipo SYNTRO | N5: Edificio/sala sin plano o coordenadas confiables; diferencias entre recorrido real y representación del mapa. | O5: Abierto | P5: 1.2 / 1.3 / 1.4 / 1.5 | Q5: 2 | R5: 4 | S5: =Q5*R5 -> 8
A6: R-02 | B6: Operacional / Estructura física | C6: Durante la implementación o las pruebas cambian edificios, salas o containers temporales y la línea base usada para validar el mapa queda desactualizada. | D6: El hospital puede arrendar, instalar, trasladar o retirar containers y modificar dependencias mientras el proyecto está en ejecución. | E6: Las pruebas de mapa, ubicación y rutas podrían ejecutarse contra una realidad física distinta y perder validez. | F6: 3 | G6: 3 | H6: =F6*G6 -> 9 | I6: =IF(H6>=15,"Crítico",IF(H6>=10,"Alto",IF(H6>=5,"Medio","Bajo"))) -> Medio | J6: Mitigar | K6: Usar la funcionalidad de crear/modificar/desactivar edificios y dependencias; auditar los cambios; acordar un corte de validación antes de UAT/pruebas finales y revisar con Infraestructura si hubo cambios desde el último levantamiento. | L6: Actualizar la estructura física, reubicar los activos afectados y repetir solo los casos de prueba impactados; registrar la nueva fecha de corte. | M6: Contraparte Infraestructura / Administrador SYNTRO | N6: Aviso de nuevo contrato/container, retiro o traslado físico; dependencia nueva no presente en el mapa durante pruebas. | O6: Abierto | P6: 1.2 / 1.4 / 1.5 / 1.6 | Q6: 2 | R6: 3 | S6: =Q6*R6 -> 6
A7: R-03 | B7: Gobernanza / Autorizaciones | C7: Las autorizaciones para acceder a redes, datos o infraestructura institucional no se obtienen a tiempo o imponen restricciones no previstas. | D7: El proyecto depende de permisos formales de las áreas responsables para operar sobre recursos institucionales. | E7: Se pueden bloquear escaneos, pruebas técnicas, uso de datos o el despliegue on-premise. | F7: 4 | G7: 5 | H7: =F7*G7 -> 20 | I7: =IF(H7>=15,"Crítico",IF(H7>=10,"Alto",IF(H7>=5,"Medio","Bajo"))) -> Crítico | J7: Mitigar | K7: Solicitar autorizaciones por escrito con anticipación; separar actividades que requieren privilegios; documentar responsable y fecha límite de cada permiso. | L7: Continuar con módulos independientes o entorno controlado y escalar el bloqueo al patrocinio funcional/institucional. | M7: Dirección del Proyecto / Contraparte TI | N7: Solicitud sin respuesta, acceso denegado o condición técnica/política no aprobada. | O7: Abierto | P7: 1.1 / 1.4 / 1.5 / 1.6 | Q7: 2 | R7: 5 | S7: =Q7*R7 -> 10
A8: R-04 | B8: Técnico / Red | C8: El escaneo de red genera carga o interferencia, afecta segmentos sensibles o Ciberseguridad lo bloquea por considerarlo riesgoso. | D8: La observabilidad de red puede requerir recorrer rangos amplios y operar bajo restricciones de seguridad y disponibilidad hospitalaria. | E8: Puede afectarse la operación de red o perderse temporalmente la capacidad de observabilidad del MVP. | F8: 3 | G8: 5 | H8: =F8*G8 -> 15 | I8: =IF(H8>=15,"Crítico",IF(H8>=10,"Alto",IF(H8>=5,"Medio","Bajo"))) -> Crítico | J8: Mitigar | K8: Usar escaneo de bajo impacto y solo sobre rangos autorizados; validar previamente en laboratorio; definir límites de concurrencia, pausado/detención y condiciones de ejecución con Redes/Ciberseguridad. | L8: Detener el escaneo, conservar resultados parciales identificados como incompletos y operar el sistema sin observabilidad hasta redefinir la configuración autorizada. | M8: Responsable Técnico / Contraparte Redes-Ciberseguridad | N8: Aumento anormal de tráfico, alertas de monitoreo, incidentes asociados al escaneo o solicitud de bloqueo. | O8: Abierto | P8: 1.3 / 1.4 / 1.5 | Q8: 2 | R8: 5 | S8: =Q8*R8 -> 10
A9: R-05 | B9: Técnico / Reconciliación | C9: Los datos observados en red (IP dinámica, MAC, hostname u otros) no permiten correlacionar de forma suficientemente confiable los equipos con el inventario. | D9: Los identificadores de red pueden cambiar, faltar o no coincidir con los registros patrimoniales. | E9: Se generan falsos positivos/negativos y disminuye la credibilidad del contraste inventario-red. | F9: 4 | G9: 3 | H9: =F9*G9 -> 12 | I9: =IF(H9>=15,"Crítico",IF(H9>=10,"Alto",IF(H9>=5,"Medio","Bajo"))) -> Alto | J9: Mitigar | K9: Definir jerarquía de claves de correlación; medir tasa de coincidencia; registrar el motivo de la sugerencia y mostrar la reconciliación como apoyo, no como error patrimonial. | L9: Mantener el registro como no conciliado y derivarlo a revisión manual sin modificar el inventario oficial. | M9: Responsable Técnico / Soporte TI | N9: Caída de la tasa de coincidencia, múltiples candidatos para un activo o discrepancias recurrentes por DHCP/hostname. | O9: Abierto | P9: 1.3 / 1.4 / 1.5 | Q9: 2 | R9: 3 | S9: =Q9*R9 -> 6
A10: R-06 | B10: Técnico / Deuda técnica | C10: El código o la base reutilizados contienen deuda técnica, dependencias obsoletas o documentación insuficiente que obligan a retrabajo. | D10: Parte de la solución ya existe y puede contener decisiones técnicas previas no documentadas o incompatibles con la línea base actual. | E10: Aumentan el tiempo de análisis/construcción, la probabilidad de defectos y la dependencia de conocimiento individual. | F10: 3 | G10: 4 | H10: =F10*G10 -> 12 | I10: =IF(H10>=15,"Crítico",IF(H10>=10,"Alto",IF(H10>=5,"Medio","Bajo"))) -> Alto | J10: Mitigar | K10: Realizar revisión técnica por módulo; documentar stack, dependencias y decisiones; clasificar qué se reutiliza, refactoriza o reemplaza antes de modificar componentes críticos. | L10: Aislar el componente afectado, priorizar corrección de deuda crítica y replanificar solo la funcionalidad dependiente. | M10: Responsable Técnico / Equipo SYNTRO | N10: Dependencia sin soporte, módulo que solo comprende una persona, comportamiento no documentado o fallos repetidos al modificar código legado. | O10: Abierto | P10: 1.3 / 1.4 | Q10: 2 | R10: 4 | S10: =Q10*R10 -> 8
A11: R-07 | B11: Infraestructura / Despliegue | C11: La infraestructura on-premise no se asigna a tiempo o el ambiente objetivo no es compatible con el stack y sus prerrequisitos. | D11: El despliegue depende de servidor/VM, sistema operativo, almacenamiento, red, respaldo, versiones y permisos institucionales. | E11: La implantación puede retrasarse o requerir ajustes tardíos del diseño técnico. | F11: 3 | G11: 5 | H11: =F11*G11 -> 15 | I11: =IF(H11>=15,"Crítico",IF(H11>=10,"Alto",IF(H11>=5,"Medio","Bajo"))) -> Crítico | J11: Mitigar | K11: Emitir prerrequisitos de infraestructura desde diseño; validar versiones y recursos con anticipación; mantener procedimiento de instalación reproducible y configuración documentada. | L11: Utilizar entorno temporal controlado para validación/demostración y reprogramar la implantación institucional hasta resolver incompatibilidades. | M11: Contraparte TI / Responsable Técnico | N11: Servidor/VM no asignado, recursos insuficientes, librería no soportada o instalación que requiere permisos/versiones no disponibles. | O11: Abierto | P11: 1.3 / 1.4 / 1.6 | Q11: 2 | R11: 5 | S11: =Q11*R11 -> 10
A12: R-08 | B12: Calidad / Auditoría | C12: La auditoría no registra información suficiente para reconstruir cambios relevantes de inventario o ubicación. | D12: El MVP utiliza los registros de auditoría como mecanismo principal de historial, sin exigir una entidad independiente de movimientos. | E12: No es posible demostrar quién cambió qué, cuándo, desde qué valor y hacia cuál, debilitando trazabilidad y criterios de éxito. | F12: 3 | G12: 4 | H12: =F12*G12 -> 12 | I12: =IF(H12>=15,"Crítico",IF(H12>=10,"Alto",IF(H12>=5,"Medio","Bajo"))) -> Alto | J12: Mitigar | K12: Definir eventos y campos auditables mínimos; registrar actor, fecha, acción, entidad y valores relevantes; proteger los logs e incluir una prueba de reconstrucción de historial. | L12: Corregir la cobertura de auditoría y reconstruir información desde fuentes auxiliares cuando sea posible. | M12: Responsable Técnico / QA | N12: Cambio relevante sin registro, log sin actor/fecha/valores o imposibilidad de reconstruir una secuencia de ubicación. | O12: Abierto | P12: 1.3 / 1.4 / 1.5 | Q12: 2 | R12: 4 | S12: =Q12*R12 -> 8
A13: R-09 | B13: Rendimiento / Usabilidad | C13: El rendimiento no se valida con un volumen representativo de activos, ubicaciones, búsquedas y auditoría acumulada. | D13: El entorno de desarrollo puede manejar menos datos que la operación prevista (aprox. 3.000 computadores e impresoras). | E13: Mapa, dashboard y búsquedas pueden presentar lentitud o degradación al implantarse. | F13: 3 | G13: 3 | H13: =F13*G13 -> 9 | I13: =IF(H13>=15,"Crítico",IF(H13>=10,"Alto",IF(H13>=5,"Medio","Bajo"))) -> Medio | J13: Mitigar | K13: Generar datos sintéticos/anonimizados a escala; fijar umbrales de respuesta; probar consultas, filtros, mapa y crecimiento de auditoría antes de aceptación. | L13: Optimizar consultas/índices, paginar/cargar de forma diferida y repetir las pruebas de rendimiento afectadas. | M13: Responsable Técnico / QA | N13: Tiempos de respuesta sobre umbral, carga incompleta del mapa o degradación al aumentar el volumen. | O13: Abierto | P13: 1.4 / 1.5 | Q13: 2 | R13: 3 | S13: =Q13*R13 -> 6
A14: R-10 | B14: Seguridad / Autenticación | C14: El mecanismo de autenticación institucional requerido no está definido o no puede integrarse con la solución (por ejemplo AD/LDAP/SSO si la institución lo exige). | D14: Las políticas institucionales pueden exigir un esquema distinto a las cuentas locales previstas. | E14: Se generan cuentas paralelas, administración manual o retrasos de seguridad antes del despliegue. | F14: 3 | G14: 3 | H14: =F14*G14 -> 9 | I14: =IF(H14>=15,"Crítico",IF(H14>=10,"Alto",IF(H14>=5,"Medio","Bajo"))) -> Medio | J14: Mitigar | K14: Confirmar tempranamente con Ciberseguridad/Infraestructura el mecanismo requerido; documentar el modelo de identidad y mantener autenticación local solo como alternativa si es formalmente aceptada. | L14: Mantener acceso local restringido en ambiente controlado hasta disponer del mecanismo institucional aprobado. | M14: Responsable Técnico / Ciberseguridad | N14: Requisito institucional de SSO/directorio aparece después del diseño o el ambiente no permite la integración prevista. | O14: Abierto | P14: 1.2 / 1.3 / 1.6 | Q14: 2 | R14: 3 | S14: =Q14*R14 -> 6
A15: R-11 | B15: Datos / Calidad y disponibilidad | C15: Las fuentes de inventario llegan duplicadas, desactualizadas, incompletas, con formatos distintos o no se entregan por restricciones contractuales/confidencialidad. | D15: La información puede provenir de planillas y distintos proveedores o responsables con criterios no homogéneos. | E15: La carga inicial no representa con suficiente confianza los activos y ubicaciones que el sistema debe gestionar. | F15: 5 | G15: 4 | H15: =F15*G15 -> 20 | I15: =IF(H15>=15,"Crítico",IF(H15>=10,"Alto",IF(H15>=5,"Medio","Bajo"))) -> Crítico | J15: Mitigar | K15: Perfilar, limpiar y validar las fuentes; registrar origen/fecha; acordar muestreo con contraparte; definir campos mínimos aceptables y contabilizar registros omitidos/rechazados. | L15: Cargar solo el subconjunto validado, documentar brechas y completar/corregir datos mediante revisión con Soporte TI y responsables de la fuente. | M15: Equipo SYNTRO / Soporte TI / Contraparte de datos | N15: Alta tasa de duplicados/rechazos, campos críticos vacíos, inconsistencias entre proveedores o fuente que no puede ser entregada. | O15: Abierto | P15: 1.2 / 1.4 / 1.5 | Q15: 3 | R15: 4 | S15: =Q15*R15 -> 12
A16: R-12 | B16: Operacional / Datos | C16: Tras la implantación no se registran oportunamente traslados de equipos, cambios de responsable ni modificaciones de la estructura física. | D16: El proceso operativo puede seguir dependiendo de registros paralelos o conocimiento informal de Soporte e Infraestructura. | E16: El inventario y el mapa vuelven a desactualizarse aunque la plataforma funcione correctamente. | F16: 4 | G16: 4 | H16: =F16*G16 -> 16 | I16: =IF(H16>=15,"Crítico",IF(H16>=10,"Alto",IF(H16>=5,"Medio","Bajo"))) -> Crítico | J16: Mitigar | K16: Incorporar la actualización de SYNTRO en los flujos operativos; asignar responsables por tipo de cambio; simplificar la edición y revisar periódicamente registros sin actualización. | L16: Realizar conciliación extraordinaria con inventario/fuentes operativas y corregir por lotes los registros desactualizados. | M16: Responsable Operacional / Soporte TI / Infraestructura | N16: Diferencias entre terreno y sistema, activos con ubicación obsoleta o cambios físicos conocidos que no aparecen registrados. | O16: Abierto | P16: 1.4 / 1.6 | Q16: 2 | R16: 4 | S16: =Q16*R16 -> 8
... A31: R-27 | B31: Pruebas / Calidad | C31: Las pruebas críticas se ejecutan demasiado tarde o en un entorno que no representa las condiciones reales del hospital. | D31: Cascada concentra la validación formal después de construcción y el ambiente institucional puede no estar disponible desde el inicio. | E31: Defectos de integración, seguridad, rendimiento o despliegue pueden aparecer cerca del cierre con poco margen de corrección. | F31: 3 | G31: 4 | H31: =F31*G31 -> 12 | I31: =IF(H31>=15,"Crítico",IF(H31>=10,"Alto",IF(H31>=5,"Medio","Bajo"))) -> Alto | J31: Mitigar | K31: Mantener Plan de Pruebas Inicial; adelantar revisiones técnicas y pruebas por componente; usar datos/volumen representativos y preparar un ambiente de prueba lo más cercano posible al objetivo. | L31: Priorizar defectos críticos, repetir los casos afectados en ambiente representativo y formalizar pendientes no críticos antes de aceptación. | M31: Responsable Técnico / QA / Dirección del Proyecto | N31: Ambiente final disponible recién al cierre, casos críticos sin ejecutar o defectos sistémicos descubiertos en pruebas finales. | O31: Abierto | P31: 1.5 / 1.6 | Q31: 2 | R31: 4 | S31: =Q31*R31 -> 8

Sheet Escalas
A1: ESCALAS DE VALORACIÓN
A3: Valor | B3: Probabilidad | C3: Criterio orientativo | E3: Valor | F3: Impacto
A4: 1 | B4: Muy baja | C4: Evento excepcional o poco probable durante el proyecto. | E4: 1 | F4: Menor: efecto acotado sin comprometer entregables.
A5: 2 | B5: Baja | C5: Podría ocurrir, pero existen condiciones favorables para evitarlo. | E5: 2 | F5: Bajo: retrabajo menor o demora recuperable.
A6: 3 | B6: Media | C6: Existe una posibilidad razonable de ocurrencia. | E6: 3 | F6: Moderado: afecta una actividad/hito y requiere corrección.
A7: 4 | B7: Alta | C7: Es probable que ocurra si no se actúa preventivamente. | E7: 4 | F7: Alto: compromete entregables, plazo, calidad o aceptación.
A8: 5 | B8: Muy alta | C8: Se espera que ocurra o ya existen señales frecuentes. | E8: 5 | F8: Crítico: puede bloquear el proyecto, afectar seguridad/datos o impedir implantación.
A10: Exposición (P×I) | B10: Nivel | C10: Criterio
A11: 1–4 | B11: Bajo | C11: Seguimiento normal.
A12: 5–9 | B12: Medio | C12: Mitigación planificada y revisión periódica.
A13: 10–14 | B13: Alto | C13: Acción prioritaria y seguimiento cercano.
A14: 15–25 | B14: Crítico | C14: Tratamiento inmediato y escalamiento si corresponde.
A16: Criterio de uso
A17: La exposición inicial representa el riesgo antes de aplicar el tratamiento propuesto. El riesgo residual estima la exposición esperada después de implementar las medidas. Los valores son una línea base para revisión: si cambia el contexto, la probabilidad, impacto o tratamiento deben actualizarse y registrarse.

Sheet Resumen
A1: RESUMEN DE RIESGOS · SYNTRO
A3: Indicador | B3: Valor | D3: ID | E3: Riesgo prioritario | F3: P | G3: I | H3: Exposición
A4: Total de riesgos | B4: 27 | D4: R-03 | E4: Las autorizaciones para acceder a redes, datos o infraestructura institucional no se obtienen a tiempo o imponen restricciones no previstas. | F4: 4 | G4: 5 | H4: 20
A5: Críticos | B5: =COUNTIF('Matriz de Riesgos'!I5:I31,"Crítico") -> 8 | D5: R-11 | E5: Las fuentes de inventario llegan duplicadas, desactualizadas, incompletas, con formatos distintos o no se entregan por restricciones contractuales/confidencialidad. | F5: 5 | G5: 4 | H5: 20
A6: Altos | B6: =COUNTIF('Matriz de Riesgos'!I5:I31,"Alto") -> 14 | D6: R-01 | E6: La información espacial inicial (planos, edificios, pisos, salas y containers) es incompleta, desactualizada o insuficientemente precisa para construir el mapa y validar rutas. | F6: 4 | G6: 4 | H6: 16
A7: Medios | B7: =COUNTIF('Matriz de Riesgos'!I5:I31,"Medio") -> 5 | D7: R-12 | E7: Tras la implantación no se registran oportunamente traslados de equipos, cambios de responsable ni modificaciones de la estructura física. | F7: 4 | G7: 4 | H7: 16
A8: Bajos | B8: =COUNTIF('Matriz de Riesgos'!I5:I31,"Bajo") -> 0 | D8: R-18 | E8: Las contrapartes y usuarios clave no están disponibles o validan tarde, bloqueando el avance entre fases de Cascada. | F8: 4 | G8: 4 | H8: 16
D9: R-25 | E9: La carga de documentación, desarrollo, pruebas y coordinación supera la capacidad disponible o concentra actividades críticas en una sola persona. | F9: 4 | G9: 4 | H9: 16
A10: Nivel | B10: Cantidad | D10: R-04 | E10: El escaneo de red genera carga o interferencia, afecta segmentos sensibles o Ciberseguridad lo bloquea por considerarlo riesgoso. | F10: 3 | G10: 5 | H10: 15
A11: Crítico | B11: =COUNTIF('Matriz de Riesgos'!I5:I31,"Crítico") -> 8 | D11: R-07 | E11: La infraestructura on-premise no se asigna a tiempo o el ambiente objetivo no es compatible con el stack y sus prerrequisitos. | F11: 3 | G11: 5 | H11: 15
A12: Alto | B12: =COUNTIF('Matriz de Riesgos'!I5:I31,"Alto") -> 14
A13: Medio | B13: =COUNTIF('Matriz de Riesgos'!I5:I31,"Medio") -> 5
A14: Bajo | B14: =COUNTIF('Matriz de Riesgos'!I5:I31,"Bajo") -> 0

Sheet Referencias
A1: FUENTES Y TRAZABILIDAD
A3: Fuente | B3: Uso en la matriz | C3: Estado | D3: Enlace
A4: Acta de Constitución SYNTRO v1.0 | B4: Contexto, alcance, gobernanza, restricciones, despliegue on-premise, telemetría y criterios de éxito. | C4: Fuente del proyecto | D4: https://docs.google.com/document/d/1Z4sQLV1Gpt-3iqLn-2WyJnP0JxsIxflW/edit
A5: Especificación de Requisitos SYNTRO v0.8 | B5: Requisitos, reglas de negocio y pendientes de alcance; destaca que la edición de edificios/salas/rutas aún debe cerrarse como decisión de MVP. | C5: Fuente del proyecto | D5: https://docs.google.com/document/d/13iLA7ADQ60W7a4FgU82ECyFPUHtXISBh/edit
A6: Guía de Artefactos Metodológicos - Cascada (SDLC) - SYNTRO | B6: Define la matriz de riesgos como artefacto formal de planificación y sus ámbitos mínimos. | C6: Fuente metodológica interna | D6: https://docs.google.com/document/d/1zvGYEDeb5kOF6Z5Hi7ye-sjMk2iLRXI9DGJW7qkIzSQ/edit
A7: EDT - Hitos de desarrollo y diccionario (WBS) | B7: Trazabilidad de los riesgos con las etapas y paquetes de trabajo. | C7: Fuente de planificación | D7: https://docs.google.com/spreadsheets/d/1r_x1ZpkI6-e_7ZTKErGfESnTzTczXmwIDsju3WPbqcM/edit
A8: Lista consolidada de 22 riesgos aportada por el equipo (11-10-2026) | B8: Se comparó con la matriz v0.1; se fusionaron duplicados, se hicieron descripciones más específicas y se incorporaron riesgos faltantes. | C8: Fuente interna del equipo | D8: Sin enlace externo
A9: Referencia visual de matriz de riesgos aportada por el equipo (12-10-2026) | B9: Inspiración de diseño para la hoja “Mapa de Riesgos”: cuadrícula 5×5 con Probabilidad en eje vertical e Impacto/Gravedad en eje horizontal. | C9: Referencia visual | D9: Imagen adjunta en la conversación del proyecto

Sheet Criterio de integración
A1: CRITERIO DE INTEGRACIÓN DE RIESGOS · v0.2
A3: Se comparó la matriz inicial con la lista de 22 riesgos aportada por el equipo. Los riesgos repetidos se fusionaron cuando compartían causa, consecuencia y tratamiento; cuando una formulación escondía dos problemas distintos, se separó para que cada riesgo tenga un disparador, responsable y respuesta verificables.
A7: Riesgo final | B7: Origen / equivalencia | C7: Decisión de integración | D7: Qué mejora | E7: Documento relacionado | F7: Observación
A8: R-01 | B8: Lista R-01 | C8: Se mantiene independiente | D8: Distingue falta de línea base espacial de cambios físicos posteriores. | E8: ERS / Plan de Pruebas | F8: Las rutas pueden quedar condicionadas a disponibilidad de geometría confiable.
A9: R-02 | B9: Matriz v0.1 R-03 + Lista R-10 | C9: Reformulado | D9: El cambio de edificios/containers no es falla de la funcionalidad: el riesgo es que cambie la realidad durante implementación/pruebas y quede obsoleto el corte de validación. | E9: ERS / Casos de Uso / Plan de Pruebas | F9: Recomendación: incluir crear/modificar/desactivar edificio/container y caso de prueba de cambio físico.
A10: R-03 | B10: Matriz v0.1 R-01 | C10: Se mantiene independiente | D10: Separa la autorización institucional del riesgo técnico propio del escaneo. | E10: Gobernanza / Implantación | F10: Afecta red, datos, pruebas y despliegue.
A11: R-04 | B11: Lista R-02 + parte de Matriz v0.1 R-06 | C11: Fusionado y precisado | D11: Se centra en impacto operativo/seguridad del escaneo, no en la calidad de correlación. | E11: ERS / Pruebas | F11: Debe probarse detención, parcialidad y límites de ejecución.
A12: R-05 | B12: Lista R-03 + parte de Matriz v0.1 R-06/R-11 | C12: Fusionado y precisado | D12: Separa calidad de correlación de la regla que impide actualizar inventario automáticamente. | E12: ERS / Reconciliación | F12: Tasa de coincidencia debe tratarse como KPI diagnóstico.
A13: R-06 | B13: Lista R-04 + Matriz v0.1 R-15/R-16 | C13: Fusionado | D13: Agrupa deuda técnica, dependencias y concentración de conocimiento técnico. | E13: Arquitectura / Desarrollo | F13: La capacidad del equipo queda tratada además en R-25.
A14: R-07 | B14: Lista R-05 + Matriz v0.1 R-08/R-16 | C14: Fusionado | D14: Consolida disponibilidad del ambiente e incompatibilidad del stack. | E14: Arquitectura / Implantación | F14: Validar prerrequisitos antes del cierre de diseño.
A15: R-08 | B15: Lista R-06 + Matriz v0.1 R-10 | C15: Fusionado | D15: Mantiene foco verificable en reconstrucción de historial. | E15: ERS / Pruebas | F15: Caso de prueba específico de auditoría.
A16: R-09 | B16: Lista R-07 + Matriz v0.1 R-14 | C16: Fusionado | D16: Añade volumen realista y crecimiento de auditoría. | E16: Plan de Pruebas | F16: Prueba con datos sintéticos/anonimizados.
A17: R-10 | B17: Lista R-08 | C17: Agregado | D17: Se formula de manera condicional: integración institucional solo si la política la exige. | E17: ERS / Seguridad | F17: No se asume AD/LDAP/SSO como requisito ya aprobado.
A18: R-11 | B18: Lista R-09 + Matriz v0.1 R-02 | C18: Fusionado y ampliado | D18: Incluye calidad, formatos heterogéneos y posible no entrega por restricciones contractuales/confidencialidad. | E18: ERS / Importación | F18: Registrar fuente y fecha.
... A34: R-27 | B34: Lista R-22 + parte de Matriz v0.1 R-13/R-14 | C34: Fusionado y precisado | D34: Separa calidad del cronograma: riesgo de descubrir defectos al final por ambiente/pruebas tardías. | E34: Plan de Pruebas | F34: Adelantar pruebas por componente.
A37: DECISIÓN / RECOMENDACIÓN · EDIFICIOS Y CONTAINERS
A38: Que el hospital agregue o retire containers no debería modelarse como un riesgo de que SYNTRO 'no soporte' cambios, porque la creación/edición de edificios y dependencias es precisamente una respuesta funcional a esa realidad. El riesgo correcto es que la configuración física cambie entre el levantamiento y las pruebas/aceptación, dejando desactualizada la línea base usada para validar el sistema. Por eso R-02 exige una fecha de corte previa a UAT/pruebas finales y una revisión con Infraestructura para detectar altas, bajas o traslados. Además, este caso debería cerrar la decisión pendiente de la ERS respecto de herramientas de edición de edificios/salas/rutas: al menos crear, modificar y desactivar edificios/containers debe quedar trazable y probado.

Sheet Mapa de Riesgos
A1: MAPA VISUAL DE RIESGOS · PROBABILIDAD × IMPACTO
A2: Representación gráfica de los 27 riesgos vigentes. El eje horizontal muestra el impacto y el eje vertical la probabilidad. El color corresponde al nivel de exposición definido en la hoja Escalas.
C4: IMPACTO / GRAVEDAD → | I4: LEYENDA
C5: 1 Menor | D5: 2 Bajo | E5: 3 Moderado | F5: 4 Alto | G5: 5 Crítico | I5: 1–4 | J5: Bajo
A6: PROBABILIDAD ↑ | B6: 5 Muy alta | C6: 5 — | D6: 10 — | E6: 15 — | F6: 20 R-11 | G6: 25 — | I6: 5–9 | J6: Medio
B7: 4 Alta | C7: 4 — | D7: 8 — | E7: 12 R-05 | F7: 16 R-01 · R-12 · R-18 · R-25 | G7: 20 R-03 | I7: 10–14 | J7: Alto
B8: 3 Media | C8: 3 — | D8: 6 — | E8: 9 R-02 · R-09 · R-10 · R-19 | F8: 12 R-06 · R-08 · R-15 · R-20 · R-22 · R-23 · R-24 · R-26 · R-27 | G8: 15 R-04 · R-07 | I8: 15–25 | J8: Crítico
B9: 2 Baja | C9: 2 — | D9: 4 — | E9: 6 — | F9: 8 R-21 | G9: 10 R-13 · R-14 · R-16 · R-17 | I9: Los códigos R-xx corresponden a la hoja “Matriz de Riesgos”. La ubicación refleja la valoración P/I de la versión 0.3.
B10: 1 Muy baja | C10: 1 — | D10: 2 — | E10: 3 — | F10: 4 — | G10: 5 —
A14: DETALLE DE RIESGOS REPRESENTADOS
A15: ID | B15: Riesgo | C15: Categoría | D15: P | E15: I | F15: Exposición | G15: Nivel | H15: Estrategia | I15: Responsable | J15: EDT
A16: R-03 | B16: Las autorizaciones para acceder a redes, datos o infraestructura institucional no se obtienen a tiempo o imponen restricciones no previstas. | C16: Gobernanza / Autorizaciones | D16: 4 | E16: 5 | F16: 20 | G16: Crítico | H16: Mitigar | I16: Dirección del Proyecto / Contraparte TI | J16: 1.1 / 1.4 / 1.5 / 1.6
A17: R-11 | B17: Las fuentes de inventario llegan duplicadas, desactualizadas, incompletas, con formatos distintos o no se entregan por restricciones contractuales/confidencialidad. | C17: Datos / Calidad y disponibilidad | D17: 5 | E17: 4 | F17: 20 | G17: Crítico | H17: Mitigar | I17: Equipo SYNTRO / Soporte TI / Contraparte de datos | J17: 1.2 / 1.4 / 1.5
A18: R-01 | B18: La información espacial inicial (planos, edificios, pisos, salas y containers) es incompleta, desactualizada o insuficientemente precisa para construir el mapa y validar rutas. | C18: Técnico / Datos espaciales | D18: 4 | E18: 4 | F18: 16 | G18: Crítico | H18: Mitigar | I18: Contraparte Infraestructura / Equipo SYNTRO | J18: 1.2 / 1.3 / 1.4 / 1.5
A19: R-12 | B19: Tras la implantación no se registran oportunamente traslados de equipos, cambios de responsable ni modificaciones de la estructura física. | C19: Operacional / Datos | D19: 4 | E19: 4 | F19: 16 | G19: Crítico | H19: Mitigar | I19: Responsable Operacional / Soporte TI / Infraestructura | J19: 1.4 / 1.6
A20: R-18 | B20: Las contrapartes y usuarios clave no están disponibles o validan tarde, bloqueando el avance entre fases de Cascada. | C20: Interesados / Cronograma | D20: 4 | E20: 4 | F20: 16 | G20: Crítico | H20: Mitigar | I20: Dirección del Proyecto | J20: 1.1 / 1.2 / 1.3 / 1.6
A21: R-25 | B21: La carga de documentación, desarrollo, pruebas y coordinación supera la capacidad disponible o concentra actividades críticas en una sola persona. | C21: Gestión / Capacidad del equipo | D21: 4 | E21: 4 | F21: 16 | G21: Crítico | H21: Mitigar | I21: Dirección del Proyecto / Equipo SYNTRO | J21: 1.1 / 1.4 / 1.5 / 1.6
A22: R-04 | B22: El escaneo de red genera carga o interferencia, afecta segmentos sensibles o Ciberseguridad lo bloquea por considerarlo riesgoso. | C22: Técnico / Red | D22: 3 | E22: 5 | F22: 15 | G22: Crítico | H22: Mitigar | I22: Responsable Técnico / Contraparte Redes-Ciberseguridad | J22: 1.3 / 1.4 / 1.5
A23: R-07 | B23: La infraestructura on-premise no se asigna a tiempo o el ambiente objetivo no es compatible con el stack y sus prerrequisitos. | C23: Infraestructura / Despliegue | D23: 3 | E23: 5 | F23: 15 | G23: Crítico | H23: Mitigar | I23: Contraparte TI / Responsable Técnico | J23: 1.3 / 1.4 / 1.6
A24: R-05 | B24: Los datos observados en red (IP dinámica, MAC, hostname u otros) no permiten correlacionar de forma suficientemente confiable los equipos con el inventario. | C24: Técnico / Reconciliación | D24: 4 | E24: 3 | F24: 12 | G24: Alto | H24: Mitigar | I24: Responsable Técnico / Soporte TI | J24: 1.3 / 1.4 / 1.5
A25: R-06 | B25: El código o la base reutilizados contienen deuda técnica, dependencias obsoletas o documentación insuficiente que obligan a retrabajo. | C25: Técnico / Deuda técnica | D25: 3 | E25: 4 | F25: 12 | G25: Alto | H25: Mitigar | I25: Responsable Técnico / Equipo SYNTRO | J25: 1.3 / 1.4
A26: R-08 | B26: La auditoría no registra información suficiente para reconstruir cambios relevantes de inventario o ubicación. | C26: Calidad / Auditoría | D26: 3 | E26: 4 | F26: 12 | G26: Alto | H26: Mitigar | I26: Responsable Técnico / QA | J26: 1.3 / 1.4 / 1.5
A27: R-15 | B27: El tratamiento de datos o la operación técnica no se alinea con normativa aplicable, políticas internas o directrices de Ciberseguridad. | C27: Cumplimiento / Legal | D27: 3 | E27: 4 | F27: 12 | G27: Alto | H27: Mitigar | I27: Dirección del Proyecto / Ciberseguridad / Contraparte institucional | J27: 1.1 / 1.2 / 1.5 / 1.6
... A42: R-21 | B42: El inventario de SYNTRO se utiliza como evidencia oficial, contractual o de auditoría sin un proceso de validación y fecha de corte. | C42: Gobernanza / Uso de información | D42: 2 | E42: 4 | F42: 8 | G42: Medio | H42: Mitigar | I42: Patrocinador funcional / Responsable Operacional | J42: 1.1 / 1.4 / 1.6
